pymqttusb_tk/__init__.py
pymqttusb_tk/main.py
pymqttusb_tk-1.0.1.dist-info/licenses/LICENCE
pymqttusb_tk-1.0.1.dist-info/METADATA
pymqttusb_tk-1.0.1.dist-info/WHEEL
pymqttusb_tk-1.0.1.dist-info/top_level.txt
pymqttusb_tk-1.0.1.dist-info/RECORD
